{
    "name": "repro",
    "main": ".open-next/worker.js",
    "compatibility_date": "2025-02-04",
    "compatibility_flags": [
        "nodejs_compat"
    ],
    "assets": {
        "directory": ".open-next/assets",
        "binding": "ASSETS"
    },
    "vars": {},
    "observability": {
        "enabled": true
    },
    "kv_namespaces": [
        {
            "binding": "NEXT_CACHE_WORKERS_KV",
            "id": ""
        }
    ],
    "d1_databases": [
        {
            "binding": "DB",
            "database_name": "verdverm",
            "database_id": "",
            "migrations_dir": "prisma/migrations"
        }
    ],
    "define": {
        "process.version": "\"v22.14.0\"",
        "process.versions": "{ \"node\": \"22.14.0\" }"
    }
}
